README.rst
setup.cfg
setup.py
nisteag/__init__.py
nisteag/entropy.py
nisteag/errors.py
nisteag.egg-info/PKG-INFO
nisteag.egg-info/SOURCES.txt
nisteag.egg-info/dependency_links.txt
nisteag.egg-info/entry_points.txt
nisteag.egg-info/requires.txt
nisteag.egg-info/top_level.txt
nisteag.egg-info/zip-safe
nisteag/scripts/__init__.py
nisteag/scripts/checkers.py
nisteag/threats/__init__.py
nisteag/threats/throttling.py
nisteag/token/__init__.py
nisteag/token/requirements/__init__.py
nisteag/token/requirements/memorized.py
tests/scripts/__init__.py
tests/scripts/test_checkers.py
tests/threats/__init__.py
tests/threats/test_throttling.py
tests/token/__init__.py
tests/token/test_entropy.py
tests/token/requirements/__init__.py
tests/token/requirements/test_memorized.py